<?xml version="1.0" encoding="utf-8"?><toc><breadcrumbs><li><a href="530ec635-d808-c5f1-ba10-e8bf815143ea.htm">Docs</a></li><li><a href="5bf6331c-a218-658a-a3bd-7bcd489609e1.htm">Touch<wbr />Socket.<wbr />Sockets</a></li><li><a href="2687c9ff-1cda-999d-2cfa-c00e30142d0f.htm">Protocol</a></li></breadcrumbs><tocItems><li><a id="5886ad6f-89bb-3d07-d2ce-539d48113d61" href="5886ad6f-89bb-3d07-d2ce-539d48113d61.htm">构造函数</a></li><li><a id="4408ac44-98af-1815-9612-cd99670f2d99" class="has-submenu" href="4408ac44-98af-1815-9612-cd99670f2d99.htm"><span data-tocFile="../toc/IDB0VC0W.xml" class="icon toggle" onclick="ToggleExpandCollapse(this); return false;"><i class="fa fa-angle-right"> </i></span>方法</a><ul class="toc-menu is-hidden"> </ul></li><li><a id="6bc77997-267b-54fd-5ad0-6d76111076ca" class="has-submenu" href="6bc77997-267b-54fd-5ad0-6d76111076ca.htm"><span data-tocFile="../toc/IDC0VC0W.xml" class="icon toggle" onclick="ToggleExpandCollapse(this); return false;"><i class="fa fa-angle-right"> </i></span>运算符</a><ul class="toc-menu is-hidden"> </ul></li><li><a id="a166366b-78dc-50f4-4ddc-9cc751a9a01d" class="has-submenu" href="a166366b-78dc-50f4-4ddc-9cc751a9a01d.htm"><span data-tocFile="../toc/IDD0VC0W.xml" class="icon toggle" onclick="ToggleExpandCollapse(this); return false;"><i class="fa fa-angle-right"> </i></span>字段</a><ul class="toc-menu is-hidden"> </ul></li></tocItems></toc>