<?xml version="1.0" encoding="utf-8"?><toc><breadcrumbs><li><a href="530ec635-d808-c5f1-ba10-e8bf815143ea.htm">Docs</a></li><li><a href="6bd098f4-7c88-a31a-e48b-613ce7814aac.htm">Touch<wbr />Socket.<wbr />Core</a></li><li><a href="7743dc26-4f7e-0da8-0f97-31b2c45b17bc.htm">File<wbr />Pool</a></li><li><a href="fef96131-33a3-5843-bdf2-876cf3450398.htm">方法</a></li></breadcrumbs><tocItems><li><a id="8fc02719-235e-3089-5642-55eb650645b3" href="8fc02719-235e-3089-5642-55eb650645b3.htm">Get<wbr />All<wbr />Paths</a></li><li><a id="1ebca8c2-a4ea-4b2f-da4a-ef31a26afddd" class="has-submenu" href="1ebca8c2-a4ea-4b2f-da4a-ef31a26afddd.htm"><span data-tocFile="../toc/IDBA0JC0C.xml" class="icon toggle" onclick="ToggleExpandCollapse(this); return false;"><i class="fa fa-angle-right"> </i></span>Get<wbr />File<wbr />Storage<wbr />For<wbr />Read</a><ul class="toc-menu is-hidden"> </ul></li><li><a id="947603c4-a62b-efeb-cb0f-5c66e74c697d" class="has-submenu" href="947603c4-a62b-efeb-cb0f-5c66e74c697d.htm"><span data-tocFile="../toc/IDCA0JC0C.xml" class="icon toggle" onclick="ToggleExpandCollapse(this); return false;"><i class="fa fa-angle-right"> </i></span>Get<wbr />File<wbr />Storage<wbr />For<wbr />Write</a><ul class="toc-menu is-hidden"> </ul></li><li><a id="3dc8014d-6389-f0d6-eee0-f73d39aeb24c" class="has-submenu" href="3dc8014d-6389-f0d6-eee0-f73d39aeb24c.htm"><span data-tocFile="../toc/IDDA0JC0C.xml" class="icon toggle" onclick="ToggleExpandCollapse(this); return false;"><i class="fa fa-angle-right"> </i></span>Get<wbr />File<wbr />Storage<wbr />Stream</a><ul class="toc-menu is-hidden"> </ul></li><li><a id="227e0ebc-cf7f-2951-8a92-517e8868a4c3" class="has-submenu" href="227e0ebc-cf7f-2951-8a92-517e8868a4c3.htm"><span data-tocFile="../toc/IDEA0JC0C.xml" class="icon toggle" onclick="ToggleExpandCollapse(this); return false;"><i class="fa fa-angle-right"> </i></span>Get<wbr />Reader</a><ul class="toc-menu is-hidden"> </ul></li><li><a id="250f2afb-f280-b7f4-a4fa-4cb2fa7d65d9" href="250f2afb-f280-b7f4-a4fa-4cb2fa7d65d9.htm">Get<wbr />Reference<wbr />Count</a></li><li><a id="9b647632-8afd-73b1-7b92-9cba085085e7" class="has-submenu" href="9b647632-8afd-73b1-7b92-9cba085085e7.htm"><span data-tocFile="../toc/IDGA0JC0C.xml" class="icon toggle" onclick="ToggleExpandCollapse(this); return false;"><i class="fa fa-angle-right"> </i></span>Get<wbr />Writer</a><ul class="toc-menu is-hidden"> </ul></li><li><a id="0f6e5940-4560-8524-117f-57c0428418fc" href="0f6e5940-4560-8524-117f-57c0428418fc.htm">Load<wbr />File<wbr />For<wbr />Cache<wbr />Read</a></li><li><a id="ceae4d76-ec04-2b85-868c-22781159dc72" href="ceae4d76-ec04-2b85-868c-22781159dc72.htm">Try<wbr />Release<wbr />File</a></li></tocItems></toc>