<?xml version="1.0" encoding="utf-8"?><toc><breadcrumbs><li><a href="530ec635-d808-c5f1-ba10-e8bf815143ea.htm">Docs</a></li><li><a href="345b4325-66c9-71ca-bbc3-ade9451315cc.htm">Touch<wbr />Socket.<wbr />Dmtp.<wbr />Asp<wbr />Net<wbr />Core</a></li><li><a href="542bd4a1-0820-3c57-6404-65fac55a2d9a.htm">Web<wbr />Socket<wbr />Dmtp<wbr />Socket<wbr />Client</a></li></breadcrumbs><tocItems><li><a id="6d0d279c-09f8-b354-0f98-6b7abb2f9175" href="6d0d279c-09f8-b354-0f98-6b7abb2f9175.htm">构造函数</a></li><li><a id="577b06ee-246e-b104-9fc0-ac3056beffcc" class="has-submenu" href="577b06ee-246e-b104-9fc0-ac3056beffcc.htm"><span data-tocFile="../toc/IDBEF.xml" class="icon toggle" onclick="ToggleExpandCollapse(this); return false;"><i class="fa fa-angle-right"> </i></span>属性</a><ul class="toc-menu is-hidden"> </ul></li><li><a id="af207c91-1e55-3d15-5e90-07a22e78c7c3" class="has-submenu" href="af207c91-1e55-3d15-5e90-07a22e78c7c3.htm"><span data-tocFile="../toc/IDCEF.xml" class="icon toggle" onclick="ToggleExpandCollapse(this); return false;"><i class="fa fa-angle-right"> </i></span>方法</a><ul class="toc-menu is-hidden"> </ul></li></tocItems></toc>