<?xml version="1.0" encoding="utf-8"?><toc><breadcrumbs><li><a href="530ec635-d808-c5f1-ba10-e8bf815143ea.htm">Docs</a></li><li><a href="b25ed868-550f-a62b-048f-be15ae713988.htm">Touch<wbr />Socket.<wbr />Dmtp.<wbr />File<wbr />Transfer</a></li><li><a href="666dab42-8950-ed99-29d4-1f654e3936f9.htm">IFile<wbr />Resource<wbr />Controller</a></li></breadcrumbs><tocItems><li><a id="d56a2dab-6547-64ed-764d-71b1b9481d69" class="has-submenu" href="d56a2dab-6547-64ed-764d-71b1b9481d69.htm"><span data-tocFile="../toc/IDATG.xml" class="icon toggle" onclick="ToggleExpandCollapse(this); return false;"><i class="fa fa-angle-right"> </i></span>方法</a><ul class="toc-menu is-hidden"> </ul></li></tocItems></toc>