<?xml version="1.0" encoding="utf-8"?><toc><breadcrumbs><li><a href="530ec635-d808-c5f1-ba10-e8bf815143ea.htm">Docs</a></li><li><a href="719246db-3f8e-7fe7-5d5f-049790f9157b.htm">Touch<wbr />Socket.<wbr />Web<wbr />Api</a></li></breadcrumbs><tocItems><li><a id="0a1e6aa6-9fb0-5b60-807d-d1fcb0681650" class="has-submenu" href="0a1e6aa6-9fb0-5b60-807d-d1fcb0681650.htm"><span data-tocFile="../toc/IDAX.xml" class="icon toggle" onclick="ToggleExpandCollapse(this); return false;"><i class="fa fa-angle-right"> </i></span>Action<wbr />Result</a><ul class="toc-menu is-hidden"> </ul></li><li><a id="c9a425c8-b603-c74c-6733-e5b0bc45dc36" class="has-submenu" href="c9a425c8-b603-c74c-6733-e5b0bc45dc36.htm"><span data-tocFile="../toc/IDBX.xml" class="icon toggle" onclick="ToggleExpandCollapse(this); return false;"><i class="fa fa-angle-right"> </i></span>Enable<wbr />Cors<wbr />Attribute</a><ul class="toc-menu is-hidden"> </ul></li><li><a id="a8afb1d9-1fab-1e8a-b76b-c1bc0bc95964" href="a8afb1d9-1fab-1e8a-b76b-c1bc0bc95964.htm">Http<wbr />Method<wbr />Type</a></li><li><a id="af25bb02-7687-2a48-014e-8de7359bb1ed" class="has-submenu" href="af25bb02-7687-2a48-014e-8de7359bb1ed.htm"><span data-tocFile="../toc/IDDX.xml" class="icon toggle" onclick="ToggleExpandCollapse(this); return false;"><i class="fa fa-angle-right"> </i></span>IHttp<wbr />Call<wbr />Context</a><ul class="toc-menu is-hidden"> </ul></li><li><a id="2d22411b-5c40-b139-79bc-0b90e386cf64" class="has-submenu" href="2d22411b-5c40-b139-79bc-0b90e386cf64.htm"><span data-tocFile="../toc/IDEX.xml" class="icon toggle" onclick="ToggleExpandCollapse(this); return false;"><i class="fa fa-angle-right"> </i></span>IWeb<wbr />Api<wbr />Call<wbr />Context</a><ul class="toc-menu is-hidden"> </ul></li><li><a id="cfa2f513-795b-0777-7a7d-a3b5d449965a" class="has-submenu" href="cfa2f513-795b-0777-7a7d-a3b5d449965a.htm"><span data-tocFile="../toc/IDFX.xml" class="icon toggle" onclick="ToggleExpandCollapse(this); return false;"><i class="fa fa-angle-right"> </i></span>IWeb<wbr />Api<wbr />Client</a><ul class="toc-menu is-hidden"> </ul></li><li><a id="f2d7eebf-b6c4-cbd3-68ef-57f38aee70e7" class="has-submenu" href="f2d7eebf-b6c4-cbd3-68ef-57f38aee70e7.htm"><span data-tocFile="../toc/IDGX.xml" class="icon toggle" onclick="ToggleExpandCollapse(this); return false;"><i class="fa fa-angle-right"> </i></span>IWeb<wbr />Api<wbr />Client<wbr />Base</a><ul class="toc-menu is-hidden"> </ul></li><li><a id="8a4ece00-e14b-6f3e-3f8e-bf005dd3178b" class="has-submenu" href="8a4ece00-e14b-6f3e-3f8e-bf005dd3178b.htm"><span data-tocFile="../toc/IDHX.xml" class="icon toggle" onclick="ToggleExpandCollapse(this); return false;"><i class="fa fa-angle-right"> </i></span>IWeb<wbr />Api<wbr />Plugin</a><ul class="toc-menu is-hidden"> </ul></li><li><a id="92a1a559-865b-34ca-e11b-d0022078287e" class="has-submenu" href="92a1a559-865b-34ca-e11b-d0022078287e.htm"><span data-tocFile="../toc/IDIX.xml" class="icon toggle" onclick="ToggleExpandCollapse(this); return false;"><i class="fa fa-angle-right"> </i></span>IWeb<wbr />Api<wbr />Plugin&lt;TClient&gt;</a><ul class="toc-menu is-hidden"> </ul></li><li><a id="4561dda7-4288-912e-79ba-df52988a56f3" class="has-submenu" href="4561dda7-4288-912e-79ba-df52988a56f3.htm"><span data-tocFile="../toc/IDJX.xml" class="icon toggle" onclick="ToggleExpandCollapse(this); return false;"><i class="fa fa-angle-right"> </i></span>Origin<wbr />Attribute</a><ul class="toc-menu is-hidden"> </ul></li><li><a id="19f673e8-3814-d93d-6a6c-ceba2021967f" class="has-submenu" href="19f673e8-3814-d93d-6a6c-ceba2021967f.htm"><span data-tocFile="../toc/IDKX.xml" class="icon toggle" onclick="ToggleExpandCollapse(this); return false;"><i class="fa fa-angle-right"> </i></span>Router<wbr />Attribute</a><ul class="toc-menu is-hidden"> </ul></li><li><a id="a2590056-381c-553d-9436-81e60dde0269" class="has-submenu" href="a2590056-381c-553d-9436-81e60dde0269.htm"><span data-tocFile="../toc/IDLX.xml" class="icon toggle" onclick="ToggleExpandCollapse(this); return false;"><i class="fa fa-angle-right"> </i></span>Web<wbr />Api<wbr />Attribute</a><ul class="toc-menu is-hidden"> </ul></li><li><a id="e350a6c2-a350-b683-33b5-b7337d7a987c" class="has-submenu" href="e350a6c2-a350-b683-33b5-b7337d7a987c.htm"><span data-tocFile="../toc/IDMX.xml" class="icon toggle" onclick="ToggleExpandCollapse(this); return false;"><i class="fa fa-angle-right"> </i></span>Web<wbr />Api<wbr />Client</a><ul class="toc-menu is-hidden"> </ul></li><li><a id="04c570c0-ff08-af4c-98f3-8d3cbd103d5d" class="has-submenu" href="04c570c0-ff08-af4c-98f3-8d3cbd103d5d.htm"><span data-tocFile="../toc/IDNX.xml" class="icon toggle" onclick="ToggleExpandCollapse(this); return false;"><i class="fa fa-angle-right"> </i></span>Web<wbr />Api<wbr />Client<wbr />Slim</a><ul class="toc-menu is-hidden"> </ul></li><li><a id="bbd8066e-53be-afd8-ecc9-61c2d3173a72" class="has-submenu" href="bbd8066e-53be-afd8-ecc9-61c2d3173a72.htm"><span data-tocFile="../toc/IDOX.xml" class="icon toggle" onclick="ToggleExpandCollapse(this); return false;"><i class="fa fa-angle-right"> </i></span>Web<wbr />Api<wbr />Dispatch<wbr />Proxy</a><ul class="toc-menu is-hidden"> </ul></li><li><a id="f427e48a-4845-5eff-caaa-d7cc56dbb52f" class="has-submenu" href="f427e48a-4845-5eff-caaa-d7cc56dbb52f.htm"><span data-tocFile="../toc/IDPX.xml" class="icon toggle" onclick="ToggleExpandCollapse(this); return false;"><i class="fa fa-angle-right"> </i></span>Web<wbr />Api<wbr />Dispatch<wbr />Proxy&lt;TClient&gt;</a><ul class="toc-menu is-hidden"> </ul></li><li><a id="26ef7211-32c3-0aa7-fd29-6a826ea1a135" class="has-submenu" href="26ef7211-32c3-0aa7-fd29-6a826ea1a135.htm"><span data-tocFile="../toc/IDQX.xml" class="icon toggle" onclick="ToggleExpandCollapse(this); return false;"><i class="fa fa-angle-right"> </i></span>Web<wbr />Api<wbr />Dispatch<wbr />Proxy&lt;TClient, TAttribute&gt;</a><ul class="toc-menu is-hidden"> </ul></li><li><a id="6ce7de28-5e0e-4422-dd7b-be116fd05a56" class="has-submenu" href="6ce7de28-5e0e-4422-dd7b-be116fd05a56.htm"><span data-tocFile="../toc/IDRX.xml" class="icon toggle" onclick="ToggleExpandCollapse(this); return false;"><i class="fa fa-angle-right"> </i></span>Web<wbr />Api<wbr />Event<wbr />Args</a><ul class="toc-menu is-hidden"> </ul></li><li><a id="ec5f33dd-84bf-222e-a097-a0d0cd214a17" class="has-submenu" href="ec5f33dd-84bf-222e-a097-a0d0cd214a17.htm"><span data-tocFile="../toc/IDSX.xml" class="icon toggle" onclick="ToggleExpandCollapse(this); return false;"><i class="fa fa-angle-right"> </i></span>Web<wbr />Api<wbr />Parser<wbr />Plugin</a><ul class="toc-menu is-hidden"> </ul></li></tocItems></toc>